{
  "config":
  {
    "minutesUntilStop":2,
    "senderAddress":"",
    "captchaURL":"/Captcha.jpg",
    "codeSnippletMicro":"<script type=\"text/javascript\" src=\"http://radiodev.de:80/info/player/player.js\"></script>\n<script type=\"text/javascript\">\nradioConfig = {play:\"@subdomain@\"};\nradioPlayer();\n</script>",
    "sliceRequired":false,
    "minutesUntilReload":10,
    "shop4Config":
    {
      "id":4,
      "enabled":false,
      "title":"",
      "icon2":"",
      "icon1":"",
      "urlTemplate":""
    },
    "codeSnippletEmbedded":"<script type=\"text/javascript\" src=\"http://radiodev.de:80/info/player/player.js\"></script>\n<script type=\"text/javascript\">\nradioConfig = {play:\"@subdomain@\"};\nradioPlayer();\n</script>",
    "minutesUntilRefreshSenderInfo":1440,
    "startPlayOnLoad":true,
    "defaultSorting":"related",
    "shop1Config":
    {
      "id":1,
      "enabled":true,
      "title":"amazonmp3.de",
      "icon2":"/inc/img/shops/amazonmp3_64x17.jpg",
      "icon1":"/inc/img/shops/amazonmp3_16x16.png",
      "urlTemplate":"http://www.amazon.de/gp/search?ie=UTF8&keywords=%ARTIST%%20-%20%TITLE%&tag=radiode09-21&index=mp3-downloads&linkCode=ur2&camp=1638&creative=6742"
    },
    "relayDisabledGlobally":false,
    "sliceLengthMillis":9984,
    "volume":100,
    "shop2Config":
    {
      "id":2,
      "enabled":true,
      "title":"iTunes",
      "icon2":"/inc/img/shops/itunes_64x17.jpg",
      "icon1":"/inc/img/shops/itunes_16x16.gif",
      "urlTemplate":"http://clk.tradedoubler.com/click?p=23761&a=1524455&url=http://phobos.apple.com/WebObjects/MZSearch.woa/wa/advancedSearchResults?songTerm=%TITLE%&artistTerm=%ARTIST%&s=143443&partnerId=2003"
    },
    "maxBroadcasts":10,
    "crossFadeURL":"-",
    "sendAFriendMessage":"Mitteilung Send-A-Friend",
    "welcomeURL":"http://www.radio.de/audioads/gateway.mp3",
    "shop3Config":
    {
      "id":3,
      "enabled":true,
      "title":"musicload",
      "icon2":"/inc/img/shops/musicload_64x17.jpg",
      "icon1":"/inc/img/shops/musicload_16x16.gif",
      "urlTemplate":"http://partners.webmasterplan.com/click.asp?ref=454996&site=3752&type=text&tnb=29&prd=yes&stext=%ARTIST% %TITLE%"
    }
  },
  "playlist":
  [
    
    {
      "overlayGraficUrl":"",
      "id":"",
      "author":"",
      "stream":"http://swr-mp3-m-dasdingraka02.akacast.akamaistream.net/7/91/137151/v1/gnl.akacast.akamaistream.net/swr-mp3-m-dasdingraka02",
      "testResult":null,
      "name":"",
      "advertisement":false,
      "audioAdId":"",
      "streamFormat":"ICECAST",
      "type":"STREAM",
      "overlayClickUrl":""
    }
  ],
  "broadcast":
  {
    "requestMetaData":true,
    "typeAsInteger":1,
    "epg":"",
    "streamFormat":"ICECAST",
    "hasLinkingAgreement":false,
    "validated":true,
    "subTitle":"",
    "seoTitle":"DASDING SPRECHSTUNDE",
    "subDomaine":"dasdingsprechstunde",
    "relayDisabled":false,
    "rank":1721,
    "playableStateString":"FREE",
    "idTeaser":0,
    "description":"Die HipHop, Black & RnB-Show auf DASDING. Hier gibt es die Interviews, News, Dates und die Deutschen Black Charts der letzten 2 Sendungen.",
    "picture2TransUrl":"http://static.radio.de/images/broadcasts/2548_2_1.png",
    "picture3TransUrl":"http://static.radio.de/images/broadcasts/2548_3_1.png",
    "longitude":0,
    "locallyEnabled":true,
    "enabled":true,
    "picture6Url":"",
    "metaDataAvailable":false,
    "globallyEnabled":true,
    "streamThrough":"BYDEMAND",
    "hasJingle":false,
    "shortDescription":"Die HipHop, Black & RnB-Show auf DASDING. Hier gibt es die Interviews, News, Dates und die Deutschen Black Charts der letzten 2 Sendungen.",
    "metaDataUrl":"http://swr-mp3-m-dasdingraka02.akacast.akamaistream.net/7/91/137151/v1/gnl.akacast.akamaistream.net/swr-mp3-m-dasdingraka02",
    "podcastUrls":
    [
      
    ],
    "latitude":0,
    "streamContentFormatAsString":"MP3",
    "bitRate":128,
    "configuredBroadcasts":
    [
      
    ],
    "picture1Set":true,
    "streamUrlOriginal":"http://mp3-live.dasding.de/dasdingraka02_m.m3u",
    "displaySubDomaine":"dasdingsprechstunde",
    "recentTitles":
    [
      
    ],
    "idType":1,
    "descriptionPodcast":"",
    "picture2Url":"",
    "documentBoost":1,
    "streamContentFormat":"MP3",
    "link":"http://www.dasding.de/#http://www.dasding.de/home/-/id=236/vv=content/87c8xx/index.html",
    "advertising":true,
    "picture1Url":"http://static.radio.de/images/broadcasts/2548_1.jpeg",
    "picture6TransUrl":"http://static.radio.de/images/broadcasts/2548_6_1.png",
    "imported":false,
    "serviceName":"broadcast",
    "lastSlice":"",
    "id":2548,
    "picture1TransUrl":"http://static.radio.de/images/broadcasts/2548_1_1.png",
    "picture5TransUrl":"http://static.radio.de/images/broadcasts/2548_5_1.png",
    "author":"",
    "title":"",
    "picture4Url":"http://static.radio.de/images/broadcasts/2548_4.jpeg",
    "picture6Set":false,
    "tagsForDisplay":
    {
      "_type":"Webradio",
      "_topic":"",
      "_country":"Deutschland",
      "_genre":"Hip-Hop, Punk",
      "_city":"Baden-Baden",
      "_family":"DASDING",
      "_continent":"Europa",
      "_language":"Deutsch"
    },
    "metaDataOverrideUrl":"",
    "localeCode":"de_DE",
    "broadcastPrograms":
    [
      
    ],
    "name":"DASDING SPRECHSTUNDE",
    "picture3Url":"",
    "streamUrl":"http://mp3-live.dasding.de/dasdingraka02_m.m3u",
    "referenceOverwriteDisabled":false,
    "sourceConnected":"false",
    "averageAmplitude":0,
    "permissionToCheck":"/radio/broadcasts",
    "picture5Set":true,
    "picture4Set":true,
    "currentProgram":null,
    "picture3Set":false,
    "picture4TransUrl":"http://static.radio.de/images/broadcasts/2548_4_1.png",
    "sampleRate":44100,
    "picture2Set":false,
    "picture5Url":"http://static.radio.de/images/broadcasts/2548_5.jpeg",
    "subdomain":"dasdingsprechstunde",
    "streamUrls":
    [
      
      {
        "sampleRate":44100,
        "id":2459243,
        "metaDataAvailable":false,
        "metaDataType":"",
        "streamContentFormat":"MP3",
        "metaDataUrl":"http://swr-mp3-m-dasdingraka02.akacast.akamaistream.net/7/91/137151/v1/gnl.akacast.akamaistream.net/swr-mp3-m-dasdingraka02",
        "streamFormat":"ICECAST",
        "streamUrl":"http://swr-mp3-m-dasdingraka02.akacast.akamaistream.net/7/91/137151/v1/gnl.akacast.akamaistream.net/swr-mp3-m-dasdingraka02",
        "idBroadcast":2548,
        "bitRate":128
      }
    ],
    "relayAvailable":true,
    "relayForIE":true
  }
}