{
  "config":
  {
    "minutesUntilStop":2,
    "senderAddress":"",
    "captchaURL":"/Captcha.jpg",
    "codeSnippletMicro":"<script type=\"text/javascript\" src=\"http://radiodev.de:80/info/player/player.js\"></script>\n<script type=\"text/javascript\">\nradioConfig = {play:\"@subdomain@\"};\nradioPlayer();\n</script>",
    "sliceRequired":false,
    "minutesUntilReload":10,
    "shop4Config":
    {
      "id":4,
      "enabled":false,
      "title":"",
      "icon2":"",
      "icon1":"",
      "urlTemplate":""
    },
    "codeSnippletEmbedded":"<script type=\"text/javascript\" src=\"http://radiodev.de:80/info/player/player.js\"></script>\n<script type=\"text/javascript\">\nradioConfig = {play:\"@subdomain@\"};\nradioPlayer();\n</script>",
    "minutesUntilRefreshSenderInfo":1440,
    "startPlayOnLoad":true,
    "defaultSorting":"related",
    "shop1Config":
    {
      "id":1,
      "enabled":true,
      "title":"amazonmp3.de",
      "icon2":"/inc/img/shops/amazonmp3_64x17.jpg",
      "icon1":"/inc/img/shops/amazonmp3_16x16.png",
      "urlTemplate":"http://www.amazon.de/gp/search?ie=UTF8&keywords=%ARTIST%%20-%20%TITLE%&tag=radiode09-21&index=mp3-downloads&linkCode=ur2&camp=1638&creative=6742"
    },
    "relayDisabledGlobally":false,
    "sliceLengthMillis":9984,
    "volume":100,
    "shop2Config":
    {
      "id":2,
      "enabled":true,
      "title":"iTunes",
      "icon2":"/inc/img/shops/itunes_64x17.jpg",
      "icon1":"/inc/img/shops/itunes_16x16.gif",
      "urlTemplate":"http://clk.tradedoubler.com/click?p=23761&a=1524455&url=http://phobos.apple.com/WebObjects/MZSearch.woa/wa/advancedSearchResults?songTerm=%TITLE%&artistTerm=%ARTIST%&s=143443&partnerId=2003"
    },
    "maxBroadcasts":10,
    "crossFadeURL":"-",
    "sendAFriendMessage":"Mitteilung Send-A-Friend",
    "welcomeURL":"http://www.radio.de/audioads/gateway.mp3",
    "shop3Config":
    {
      "id":3,
      "enabled":true,
      "title":"musicload",
      "icon2":"/inc/img/shops/musicload_64x17.jpg",
      "icon1":"/inc/img/shops/musicload_16x16.gif",
      "urlTemplate":"http://partners.webmasterplan.com/click.asp?ref=454996&site=3752&type=text&tnb=29&prd=yes&stext=%ARTIST% %TITLE%"
    }
  },
  "playlist":
  [
    
    {
      "overlayGraficUrl":"",
      "id":"",
      "author":"",
      "stream":"http://stream.schlagerhoelle.de:30842",
      "testResult":null,
      "name":"",
      "advertisement":false,
      "audioAdId":"",
      "streamFormat":"SHOUTCAST",
      "type":"STREAM",
      "overlayClickUrl":""
    }
  ],
  "broadcast":
  {
    "requestMetaData":true,
    "typeAsInteger":1,
    "epg":"",
    "streamFormat":"SHOUTCAST",
    "hasLinkingAgreement":false,
    "validated":true,
    "subTitle":"",
    "seoTitle":"RMNschlagerhölle",
    "subDomaine":"schlagerhoelle",
    "relayDisabled":false,
    "rank":171,
    "playableStateString":"FREE",
    "idTeaser":0,
    "description":"Die ganze Welt des Schlager! Mit diesem Sender feiern Sie eine himmlische Schlager Party.",
    "picture2TransUrl":"http://static.radio.de/images/broadcasts/2293_2_1.png",
    "picture3TransUrl":"http://static.radio.de/images/broadcasts/2293_3_1.png",
    "longitude":7.04906,
    "locallyEnabled":true,
    "enabled":true,
    "picture6Url":"http://static.radio.de/images/broadcasts/2293_6.jpeg",
    "metaDataAvailable":true,
    "globallyEnabled":true,
    "streamThrough":"BYDEMAND",
    "hasJingle":true,
    "shortDescription":"Die ganze Welt des Schlager! Mit diesem Sender feiern Sie eine himmlische Schlager Party.",
    "metaDataUrl":"http://stream.schlagerhoelle.de:30842",
    "podcastUrls":
    [
      
    ],
    "latitude":49.14404,
    "streamContentFormatAsString":"MP3",
    "bitRate":128,
    "configuredBroadcasts":
    [
      
    ],
    "picture1Set":true,
    "streamUrlOriginal":"http://stream.schlagerhoelle.de:30842",
    "displaySubDomaine":"schlagerhoelle",
    "recentTitles":
    [
      "#",
      "Andre Stade - Schenk Deinen Traeumen Wieder Fluegel",
      "The Hubbubs - Hello Mr. Sir",
      "[RMN] audimark - audimark Werbeblock",
      "Rex Gildo - Du Bist Mein Wunder",
      "Andrea Rischka - Wenn Du Wuesstest, Wie Sehr Ich Dich Liebe",
      "[RMN] Schlagerhoelle - wuenscht viel Vergnuegen beim naechsten Musikwunsch",
      "Duo Goldstars - Es war die Nacht",
      "Peter Alexander - Ich Schau Dir So Gern In Die Augen",
      "G.G. Anderson - Du Bist Die Sonne",
      "[RMN] - wetter",
      "[RMN] - News",
      "Howard Carpendale - Lisa ist da",
      "Roland Kaiser - Ich Glaub Es Geht Schon Wieder Los",
      "IBO - Ibiza",
      "Roy Black - Bleib bei mir",
      "Die Paldauer - Na endlich Du",
      "Oliver Lukas - Engel aus dem Sueden",
      "Schwesterherz - Ich Wr So Gern Der Grund",
      "Die Flippers - Drei Toene Am Piano",
      "Janosch Rosenberg - Susie Darling",
      "Hein Simons - Lena",
      "Cliff Richard - Ein Girl wie Du",
      "Andy Borg - Weil Wir Uns Lieben",
      "Gaby Albrecht - Der Wind Hat Mir Ein Lied Erzaehlt",
      "Udo Wenders - Theresa",
      "Roberto Delgado - Pata Pata",
      "Nicki - Wenn i mit Dir tanz",
      "Stefanie Hertel - Ganz Einfach Was Verruecktes Tun",
      "Christoff - Das 1.000 Sterne Hotel",
      "Bernd Spier - Fremde Augen",
      "Peter Sebastian - Lass Uns Diesen Weg Weitergehen",
      "Semino Rossi - Du bist meine Symphonie",
      "Bata Illic - Malaika",
      "Mara Kayser - Der Kosmos wirds schon richten",
      "Fernando Express - Pretty Flamingo",
      "Roger Whittaker - Was Ist Dabei Wenn Wir Zwei Uns Lieben",
      "Michael Morgan - Fuer Einmal Und Fuer Immer",
      "Waikikis - Hawaii Tattoo",
      "Petra Frey - Liebst Du Mich",
      "Santiano - Weit uebers Meer",
      "Marty Kessler - Das Universum",
      "Melanie Miric - Ich Vermiss Dich",
      "Rainer Hoeglmeier - Strassencafefeeling",
      "Siw Malmkvist - Frech gekuesst ist halb gewonnen",
      "Cora - Amsterdam",
      "Juergen Renfordt - No Amigo No",
      "Geschwister Hofmann - Lass mich heute abend nicht allein",
      "Nik P. - Der Mann im Mond",
      "Ireen Sheer - Dann Kamst Du",
      "Michael Stein - Sandy Goodbye",
      "Norman Langen - Mit dir war das alles am schoensten",
      "Vicky Leandros - Ich Brauch Deine Liebe",
      "Captain Cook und seine singenden Saxophone - Ich haett getanzt heut Nacht",
      "Kristina Bach - Du Warst Doch Mal Mein Mann",
      "Denise - Schenk Mir Keine Rosen",
      "[RMN] - SH - HookPromo2013 1",
      "Simone Christ - Wenn Du Mich Kuesst",
      "Susan Ebrahimi - Weil ich gluecklich bin",
      "Claudia Pletz - Freu dich auf sonnige Zeiten",
      "Freddy Quinn - Loreen",
      "Cagey Strings - Bossa Nova Baby",
      "Francine Jordi - Halt mich noch ein bisschen fest",
      "Christian Anders - Einsamkeit hat viele Namen",
      "Andy Borg - Es War Sonntag",
      "Christoff - Du Bist Ein Feuerwerk",
      "Ulli Bastian - Wie Kannst Du Es Wagen",
      "Mick Dorth - Klassic Dancer Part II",
      "Florian Haidt - Das Tu Ich So Gerne Fuer Dich"
    ],
    "idType":1,
    "descriptionPodcast":"",
    "picture2Url":"",
    "documentBoost":3,
    "streamContentFormat":"MP3",
    "link":"http://www.schlagerhoelle.de",
    "advertising":true,
    "picture1Url":"http://static.radio.de/images/broadcasts/2293_1.jpeg",
    "picture6TransUrl":"http://static.radio.de/images/broadcasts/2293_6_1.png",
    "imported":false,
    "serviceName":"broadcast",
    "lastSlice":"",
    "id":2293,
    "picture1TransUrl":"http://static.radio.de/images/broadcasts/2293_1_1.png",
    "picture5TransUrl":"http://static.radio.de/images/broadcasts/2293_5_1.png",
    "author":"",
    "title":"",
    "picture4Url":"http://static.radio.de/images/broadcasts/2293_4.jpeg",
    "picture6Set":true,
    "tagsForDisplay":
    {
      "_type":"Webradio",
      "_topic":"Webradio",
      "_country":"Deutschland",
      "_genre":"Schlager",
      "_city":"Kleinblittersdorf",
      "_family":"",
      "_continent":"Europa",
      "_language":"Deutsch"
    },
    "metaDataOverrideUrl":"",
    "localeCode":"de_DE",
    "broadcastPrograms":
    [
      
    ],
    "name":"RMNschlagerhoelle",
    "picture3Url":"",
    "streamUrl":"http://stream.schlagerhoelle.de:30842",
    "referenceOverwriteDisabled":false,
    "sourceConnected":"false",
    "averageAmplitude":0,
    "permissionToCheck":"/radio/broadcasts",
    "picture5Set":true,
    "picture4Set":true,
    "currentProgram":null,
    "picture3Set":false,
    "picture4TransUrl":"http://static.radio.de/images/broadcasts/2293_4_1.png",
    "sampleRate":44100,
    "picture2Set":false,
    "picture5Url":"http://static.radio.de/images/broadcasts/2293_5.jpeg",
    "subdomain":"schlagerhoelle",
    "streamUrls":
    [
      
      {
        "sampleRate":44100,
        "id":1252,
        "metaDataAvailable":true,
        "metaDataType":"",
        "streamContentFormat":"MP3",
        "metaDataUrl":"http://stream.schlagerhoelle.de:30842",
        "streamFormat":"SHOUTCAST",
        "streamUrl":"http://stream.schlagerhoelle.de:30842",
        "idBroadcast":2293,
        "bitRate":128
      }
    ],
    "relayAvailable":true,
    "relayForIE":true
  }
}